{
  "conversation_id": "conv_human_human_personachat_0008",
  "condition": "human_human",
  "model_a": "human",
  "model_b": "human",
  "system_prompt_a": "PersonaChat crowdsourced conversation",
  "system_prompt_b": "PersonaChat crowdsourced conversation",
  "opening_prompt_id": "PC",
  "temperature": null,
  "max_turns": 15,
  "timestamp_start": null,
  "timestamp_end": null,
  "turns": [
    {
      "turn_number": 1,
      "speaker": "model_a",
      "model": "human",
      "content": "hi how are you today",
      "token_count": 5,
      "response_time_ms": 0,
      "is_opening_prompt": true
    },
    {
      "turn_number": 2,
      "speaker": "model_b",
      "model": "human",
      "content": "doing great . i had the day off , you ?",
      "token_count": 11,
      "response_time_ms": 0,
      "is_opening_prompt": false
    },
    {
      "turn_number": 3,
      "speaker": "model_a",
      "model": "human",
      "content": "i only worked half a day i work at the bank",
      "token_count": 11,
      "response_time_ms": 0,
      "is_opening_prompt": false
    },
    {
      "turn_number": 4,
      "speaker": "model_b",
      "model": "human",
      "content": "that is nice . i work a lot",
      "token_count": 8,
      "response_time_ms": 0,
      "is_opening_prompt": false
    },
    {
      "turn_number": 5,
      "speaker": "model_a",
      "model": "human",
      "content": "what do you do ?",
      "token_count": 5,
      "response_time_ms": 0,
      "is_opening_prompt": false
    },
    {
      "turn_number": 6,
      "speaker": "model_b",
      "model": "human",
      "content": "just office work , but it is a lot",
      "token_count": 9,
      "response_time_ms": 0,
      "is_opening_prompt": false
    },
    {
      "turn_number": 7,
      "speaker": "model_a",
      "model": "human",
      "content": "oh ok i'm a teller was the best job i could find with no college",
      "token_count": 15,
      "response_time_ms": 0,
      "is_opening_prompt": false
    },
    {
      "turn_number": 8,
      "speaker": "model_b",
      "model": "human",
      "content": "a bank teller is a good job .",
      "token_count": 8,
      "response_time_ms": 0,
      "is_opening_prompt": false
    },
    {
      "turn_number": 9,
      "speaker": "model_a",
      "model": "human",
      "content": "yes it does pay the bills",
      "token_count": 6,
      "response_time_ms": 0,
      "is_opening_prompt": false
    },
    {
      "turn_number": 10,
      "speaker": "model_b",
      "model": "human",
      "content": "when i'm not working i play basket ball what do you do for fun",
      "token_count": 14,
      "response_time_ms": 0,
      "is_opening_prompt": false
    },
    {
      "turn_number": 11,
      "speaker": "model_a",
      "model": "human",
      "content": "i hike at the park",
      "token_count": 5,
      "response_time_ms": 0,
      "is_opening_prompt": false
    },
    {
      "turn_number": 12,
      "speaker": "model_b",
      "model": "human",
      "content": "that sounds relaxing , i suppose",
      "token_count": 6,
      "response_time_ms": 0,
      "is_opening_prompt": false
    },
    {
      "turn_number": 13,
      "speaker": "model_a",
      "model": "human",
      "content": "i love nature and it keeps my mind off things . do you travel",
      "token_count": 14,
      "response_time_ms": 0,
      "is_opening_prompt": false
    },
    {
      "turn_number": 14,
      "speaker": "model_b",
      "model": "human",
      "content": "not much . i should though while i'm young",
      "token_count": 9,
      "response_time_ms": 0,
      "is_opening_prompt": false
    },
    {
      "turn_number": 15,
      "speaker": "model_a",
      "model": "human",
      "content": "i want to go to another country at least once . i have never left the states",
      "token_count": 17,
      "response_time_ms": 0,
      "is_opening_prompt": false
    }
  ],
  "metadata": {
    "detective_guess": null,
    "detective_correct": null,
    "reverse_verdict_a": null,
    "reverse_verdict_b": null,
    "total_tokens_used": 143,
    "total_cost_usd": 0,
    "source": "AlekseyKorshuk/persona-chat"
  }
}